README.md
setup.py
dubboz/__init__.py
dubboz.egg-info/PKG-INFO
dubboz.egg-info/SOURCES.txt
dubboz.egg-info/dependency_links.txt
dubboz.egg-info/requires.txt
dubboz.egg-info/top_level.txt
dubboz.egg-info/zip-safe