Metadata-Version: 2.1
Name: dubboz
Version: 0.13
Summary: Easy use for dubbo python client
Home-page: https://github.com/hanzhichao/dubboz
Author: Han Zhichao
Author-email: superhin@126.com
License: MIT license
Keywords: dubboz,dubbo,python dubbo
Platform: UNKNOWN
Classifier: Programming Language :: Python
Classifier: Programming Language :: Python :: 2.7
Classifier: Programming Language :: Python :: 3.7
